bbrecon/__init__.py
bbrecon/api/__init__.py
bbrecon/api/domains.py
bbrecon/api/notifications.py
bbrecon/api/programs.py
bbrecon/client.py
bbrecon/errors.py
bbrecon/manager.py
bbrecon/models/__init__.py
bbrecon/models/domain.py
bbrecon/models/domains.py
bbrecon/models/notification.py
bbrecon/models/notifications.py
bbrecon/models/program.py
bbrecon/models/program_scope.py
bbrecon/models/programs.py
bbrecon/py.typed
bbrecon/utils.py
bin/__init__.py
bin/app.py
bin/utils/config.py
bin/utils/update.py
bbrecon-0.2.1.dist-info/entry_points.txt
bbrecon-0.2.1.dist-info/WHEEL
bbrecon-0.2.1.dist-info/METADATA
bbrecon-0.2.1.dist-info/RECORD
