Metadata-Version: 2.1
Name: bbrecon
Version: 0.2.1
Summary: A client library and CLI for accessing the Bug Bounty Recon API
Requires-Python: >=3.8,<4.0
Classifier: Programming Language :: Python :: 3
Classifier: Programming Language :: Python :: 3.8
Requires-Dist: httpx (>=0.13.3,<0.14.0)
Requires-Dist: pydantic (>=1.6.1,<2.0.0)
Requires-Dist: tabulate (>=0.8.7,<0.9.0)
Requires-Dist: typer[all] (>=0.3.1,<0.4.0)
